Workbook

Sheet Transactions
A1: Date | B1: Category | C1: Region | D1: Channel | E1: Amount | F1: Month | H1: Source: simulated transaction ledger for portfolio demonstration (see README).
A2: 45658 | B2: Revenue - Services | C2: West | D2: Card | E2: 5297.85 | F2: =TEXT(A2,"mmm-yyyy") -> Jan-2025
A3: 45658 | B3: Revenue - Services | C3: West | D3: Check | E3: 9501.94 | F3: =TEXT(A3,"mmm-yyyy") -> Jan-2025
A4: 45659 | B4: Revenue - Sales | C4: South | D4: Wire | E4: 6736.94 | F4: =TEXT(A4,"mmm-yyyy") -> Jan-2025
A5: 45659 | B5: Revenue - Sales | C5: East | D5: ACH | E5: 2973.5 | F5: =TEXT(A5,"mmm-yyyy") -> Jan-2025
A6: 45660 | B6: Professional Services | C6: East | D6: Card | E6: -4802.01 | F6: =TEXT(A6,"mmm-yyyy") -> Jan-2025
A7: 45660 | B7: Utilities | C7: North | D7: Card | E7: -5111.2 | F7: =TEXT(A7,"mmm-yyyy") -> Jan-2025
A8: 45661 | B8: Revenue - Sales | C8: West | D8: Check | E8: 7232.31 | F8: =TEXT(A8,"mmm-yyyy") -> Jan-2025
A9: 45662 | B9: Payroll | C9: East | D9: Wire | E9: -4043.69 | F9: =TEXT(A9,"mmm-yyyy") -> Jan-2025
A10: 45662 | B10: Revenue - Sales | C10: South | D10: ACH | E10: 9544.24 | F10: =TEXT(A10,"mmm-yyyy") -> Jan-2025
A11: 45663 | B11: Travel | C11: West | D11: Card | E11: -2178.73 | F11: =TEXT(A11,"mmm-yyyy") -> Jan-2025
A12: 45664 | B12: Travel | C12: East | D12: Wire | E12: -2422.98 | F12: =TEXT(A12,"mmm-yyyy") -> Jan-2025
A13: 45664 | B13: Software/SaaS | C13: South | D13: Wire | E13: -2634.58 | F13: =TEXT(A13,"mmm-yyyy") -> Jan-2025
... A421: 45930 | B421: Rent | C421: South | D421: Card | E421: -3738.11 | F421: =TEXT(A421,"mmm-yyyy") -> Sep-2025

Sheet Assumptions
A1: Monthly Budget Assumptions
A2: Blue = input cell (edit here). Black = formula. Summary tab scales these x9 (Jan-Sep) to compare against actuals.
A4: Category | B4: Monthly Budget ($)
A5: Payroll | B5: -19000
A6: Rent | B6: -7500
A7: Marketing | B7: -11500
A8: Software/SaaS | B8: -9500
A9: Travel | B9: -6200
A10: Office Supplies | B10: -6800
A11: Professional Services | B11: -11000
A12: Utilities | B12: -4200

Sheet Summary
A1: Financial KPI Summary — Jan–Sep 2025
A2: All figures computed live via SUMIFS/INDEX-MATCH from the Transactions tab.
A4: Total Revenue | B4: =SUMIFS(Transactions!E2:E421,Transactions!B2:B421,"Revenue - Sales")+SUMIFS(Transactions!E2:E421,Transactions!B2:B421,"Revenue - Services") -> 1481191.3
A5: Total Expenses | B5: =SUMIFS(Transactions!E2:E421,Transactions!E2:E421,"<0") -> -656003.76
A6: Net Income | B6: =B4+B5 -> 825187.56
A7: Avg Monthly Burn | B7: =B5/9 -> -72889.307
A9: Category | B9: Actual ($) | C9: Budget, 9-mo ($) | D9: Variance ($) | E9: Variance (%)
A10: Payroll | B10: =SUMIFS(Transactions!E2:E421,Transactions!B2:B421,A10) -> -172136.27 | C10: =INDEX(Assumptions!$B$5:$B$12,MATCH(A10,Assumptions!$A$5:$A$12,0))*9 -> -171000 | D10: =B10-C10 -> -1136.27 | E10: =IFERROR(D10/ABS(C10),"n/a") -> -0.0066448538
A11: Rent | B11: =SUMIFS(Transactions!E2:E421,Transactions!B2:B421,A11) -> -63242.94 | C11: =INDEX(Assumptions!$B$5:$B$12,MATCH(A11,Assumptions!$A$5:$A$12,0))*9 -> -67500 | D11: =B11-C11 -> 4257.06 | E11: =IFERROR(D11/ABS(C11),"n/a") -> 0.063067556
A12: Marketing | B12: =SUMIFS(Transactions!E2:E421,Transactions!B2:B421,A12) -> -100476 | C12: =INDEX(Assumptions!$B$5:$B$12,MATCH(A12,Assumptions!$A$5:$A$12,0))*9 -> -103500 | D12: =B12-C12 -> 3024 | E12: =IFERROR(D12/ABS(C12),"n/a") -> 0.029217391
A13: Software/SaaS | B13: =SUMIFS(Transactions!E2:E421,Transactions!B2:B421,A13) -> -80513.48 | C13: =INDEX(Assumptions!$B$5:$B$12,MATCH(A13,Assumptions!$A$5:$A$12,0))*9 -> -85500 | D13: =B13-C13 -> 4986.52 | E13: =IFERROR(D13/ABS(C13),"n/a") -> 0.058321871
A14: Travel | B14: =SUMIFS(Transactions!E2:E421,Transactions!B2:B421,A14) -> -51974.82 | C14: =INDEX(Assumptions!$B$5:$B$12,MATCH(A14,Assumptions!$A$5:$A$12,0))*9 -> -55800 | D14: =B14-C14 -> 3825.18 | E14: =IFERROR(D14/ABS(C14),"n/a") -> 0.068551613
A15: Office Supplies | B15: =SUMIFS(Transactions!E2:E421,Transactions!B2:B421,A15) -> -50747.29 | C15: =INDEX(Assumptions!$B$5:$B$12,MATCH(A15,Assumptions!$A$5:$A$12,0))*9 -> -61200 | D15: =B15-C15 -> 10452.71 | E15: =IFERROR(D15/ABS(C15),"n/a") -> 0.17079592
A16: Professional Services | B16: =SUMIFS(Transactions!E2:E421,Transactions!B2:B421,A16) -> -90585.22 | C16: =INDEX(Assumptions!$B$5:$B$12,MATCH(A16,Assumptions!$A$5:$A$12,0))*9 -> -99000 | D16: =B16-C16 -> 8414.78 | E16: =IFERROR(D16/ABS(C16),"n/a") -> 0.084997778
A17: Utilities | B17: =SUMIFS(Transactions!E2:E421,Transactions!B2:B421,A17) -> -31638.51 | C17: =INDEX(Assumptions!$B$5:$B$12,MATCH(A17,Assumptions!$A$5:$A$12,0))*9 -> -37800 | D17: =B17-C17 -> 6161.49 | E17: =IFERROR(D17/ABS(C17),"n/a") -> 0.16300238
A20: Monthly Revenue vs. Expenses
A21: Month | B21: Revenue | C21: Expenses
A22: Jan-2025 | B22: =SUMIFS(Transactions!$E$2:$E$421,Transactions!$F$2:$F$421,A22,Transactions!$B$2:$B$421,"Revenue - Sales")+SUMIFS(Transactions!$E$2:$E$421,Transactions!$F$2:$F$421,A22,Transactions!$B$2:$B$421,"Revenue - Services") -> 178225.11 | C22: =SUMIFS(Transactions!$E$2:$E$421,Transactions!$F$2:$F$421,A22,Transactions!$E$2:$E$421,"<0") -> -86274
A23: Feb-2025 | B23: =SUMIFS(Transactions!$E$2:$E$421,Transactions!$F$2:$F$421,A23,Transactions!$B$2:$B$421,"Revenue - Sales")+SUMIFS(Transactions!$E$2:$E$421,Transactions!$F$2:$F$421,A23,Transactions!$B$2:$B$421,"Revenue - Services") -> 204406.12 | C23: =SUMIFS(Transactions!$E$2:$E$421,Transactions!$F$2:$F$421,A23,Transactions!$E$2:$E$421,"<0") -> -70115.87
A24: Mar-2025 | B24: =SUMIFS(Transactions!$E$2:$E$421,Transactions!$F$2:$F$421,A24,Transactions!$B$2:$B$421,"Revenue - Sales")+SUMIFS(Transactions!$E$2:$E$421,Transactions!$F$2:$F$421,A24,Transactions!$B$2:$B$421,"Revenue - Services") -> 131739.17 | C24: =SUMIFS(Transactions!$E$2:$E$421,Transactions!$F$2:$F$421,A24,Transactions!$E$2:$E$421,"<0") -> -68621.2
A25: Apr-2025 | B25: =SUMIFS(Transactions!$E$2:$E$421,Transactions!$F$2:$F$421,A25,Transactions!$B$2:$B$421,"Revenue - Sales")+SUMIFS(Transactions!$E$2:$E$421,Transactions!$F$2:$F$421,A25,Transactions!$B$2:$B$421,"Revenue - Services") -> 115018.07 | C25: =SUMIFS(Transactions!$E$2:$E$421,Transactions!$F$2:$F$421,A25,Transactions!$E$2:$E$421,"<0") -> -68878.74
A26: May-2025 | B26: =SUMIFS(Transactions!$E$2:$E$421,Transactions!$F$2:$F$421,A26,Transactions!$B$2:$B$421,"Revenue - Sales")+SUMIFS(Transactions!$E$2:$E$421,Transactions!$F$2:$F$421,A26,Transactions!$B$2:$B$421,"Revenue - Services") -> 213025.24 | C26: =SUMIFS(Transactions!$E$2:$E$421,Transactions!$F$2:$F$421,A26,Transactions!$E$2:$E$421,"<0") -> -67462.67
A27: Jun-2025 | B27: =SUMIFS(Transactions!$E$2:$E$421,Transactions!$F$2:$F$421,A27,Transactions!$B$2:$B$421,"Revenue - Sales")+SUMIFS(Transactions!$E$2:$E$421,Transactions!$F$2:$F$421,A27,Transactions!$B$2:$B$421,"Revenue - Services") -> 196832 | C27: =SUMIFS(Transactions!$E$2:$E$421,Transactions!$F$2:$F$421,A27,Transactions!$E$2:$E$421,"<0") -> -50198.83
A28: Jul-2025 | B28: =SUMIFS(Transactions!$E$2:$E$421,Transactions!$F$2:$F$421,A28,Transactions!$B$2:$B$421,"Revenue - Sales")+SUMIFS(Transactions!$E$2:$E$421,Transactions!$F$2:$F$421,A28,Transactions!$B$2:$B$421,"Revenue - Services") -> 194842.48 | C28: =SUMIFS(Transactions!$E$2:$E$421,Transactions!$F$2:$F$421,A28,Transactions!$E$2:$E$421,"<0") -> -69978.48
A29: Aug-2025 | B29: =SUMIFS(Transactions!$E$2:$E$421,Transactions!$F$2:$F$421,A29,Transactions!$B$2:$B$421,"Revenue - Sales")+SUMIFS(Transactions!$E$2:$E$421,Transactions!$F$2:$F$421,A29,Transactions!$B$2:$B$421,"Revenue - Services") -> 133552.37 | C29: =SUMIFS(Transactions!$E$2:$E$421,Transactions!$F$2:$F$421,A29,Transactions!$E$2:$E$421,"<0") -> -101694.72
A30: Sep-2025 | B30: =SUMIFS(Transactions!$E$2:$E$421,Transactions!$F$2:$F$421,A30,Transactions!$B$2:$B$421,"Revenue - Sales")+SUMIFS(Transactions!$E$2:$E$421,Transactions!$F$2:$F$421,A30,Transactions!$B$2:$B$421,"Revenue - Services") -> 113550.76 | C30: =SUMIFS(Transactions!$E$2:$E$421,Transactions!$F$2:$F$421,A30,Transactions!$E$2:$E$421,"<0") -> -72779.25

Sheet Dashboard
A1: Executive Dashboard — Finance KPIs
A2: All charts are linked to the Summary tab and update automatically.
